phreeqpython/__init__.py
phreeqpython/equilibriumphase.py
phreeqpython/gas.py
phreeqpython/phreeqpython.py
phreeqpython/solution.py
phreeqpython/test.py
phreeqpython/utility.py
phreeqpython/viphreeqc.py
phreeqpython/database/.DS_Store
phreeqpython/database/Amm.dat
phreeqpython/database/phreeqc.dat
phreeqpython/database/phreeqc.log
phreeqpython/database/pitzer.dat
phreeqpython/database/test.inp
phreeqpython/database/test.inp.out
phreeqpython/database/vitens.dat
phreeqpython/database/wateq4f_PWN.dat
phreeqpython/lib/.DS_Store
phreeqpython/lib/readme.txt
phreeqpython/lib/viphreeqc.dll
phreeqpython/lib/viphreeqc.dylib
phreeqpython/lib/viphreeqc.dylib-old
phreeqpython/lib/viphreeqc.so
phreeqpython-1.5.7.dist-info/LICENCE
phreeqpython-1.5.7.dist-info/METADATA
phreeqpython-1.5.7.dist-info/WHEEL
phreeqpython-1.5.7.dist-info/top_level.txt
phreeqpython-1.5.7.dist-info/RECORD
