Metadata-Version: 2.1
Name: phreeqpython
Version: 1.5.7
Summary: Vitens viphreeqc wrapper and utilities
Home-page: https://github.com/Vitens/phreeqpython
Author: Abel Heinsbroek
Author-email: abel.heinsbroek@vitens.nl
License: Apache Licence 2.0
License-File: LICENCE
Requires-Dist: periodictable
